{
	"id": "00000000-29e9-0000-9028-00009b21ce6c",
	"architectureId": 0,
	"customerActionRequired": true,
	"cveNumber": "ADV170013",
	"cweDetailsList": [],
	"cweList": [],
	"impact": "Remote Code Execution",
	"impactId": 100000005,
	"initialReleaseDate": "2017-09-12T07:00:00Z",
	"isMariner": false,
	"kbArticles": [
		{
			"affectedBinaries": [],
			"articleName": "4038806",
			"articleUrl": "https://support.microsoft.com/help/4038806",
			"downloadName": "Security Update",
			"downloadUrl": "https://catalog.update.microsoft.com/v7/site/Search.aspx?q=KB4038806",
			"ordinal": 1,
			"rebootRequired": "Yes",
			"supercedence": "4034662"
		}
	],
	"platform": "Windows 10 for 32-bit Systems",
	"platformId": 10729,
	"product": "Adobe Flash Player",
	"productFamily": "Other",
	"productFamilyId": 100000000,
	"productId": 10384,
	"releaseDate": "2017-09-12T07:00:00Z",
	"severity": "Critical",
	"severityId": 100000000
}
