{
	"id": "00000000-0000-0000-6a29-00006170ee6a",
	"architecture": "x64",
	"architectureId": 2,
	"baseProductName": "Microsoft Office 2013 Service Pack 1",
	"baseProductVersion": "15.0.0",
	"cpe": "cpe:2.3:a:microsoft:office:2013:sp1:*:*:*:*:x64:*",
	"customerActionRequired": true,
	"cveNumber": "ADV230003",
	"cweDetailsList": [],
	"cweList": [],
	"impact": "Defense in Depth",
	"impactId": 100000000,
	"initialReleaseDate": "2023-08-08T07:00:00Z",
	"isMariner": false,
	"issuingCna": "Microsoft",
	"kbArticles": [
		{
			"affectedBinaries": [],
			"articleName": "5002439",
			"articleUrl": "https://support.microsoft.com/help/5002439",
			"downloadName": "Security Update",
			"downloadUrl": "https://www.microsoft.com/download/details.aspx?familyid=3ebcbd96-68f7-4d48-8aab-6d5f9a7d317e",
			"fixedBuildNumber": "15.0.5579.1001",
			"ordinal": 0,
			"rebootRequired": "Maybe"
		}
	],
	"platformId": 0,
	"product": "Microsoft Office 2013 Service Pack 1 (64-bit editions)",
	"productFamily": "Microsoft Office",
	"productFamilyId": 100000007,
	"productId": 10602,
	"releaseDate": "2023-08-08T07:00:00Z",
	"releaseNumber": "2023-Aug",
	"severity": "Moderate",
	"severityId": 100000002
}
